rtl/sha256_core.v
/*
 * SHA-256 Core Implementation
 *
 * This is an iterative implementation that processes one 512-bit block at a time.
 * It performs 64 rounds sequentially (one round per clock cycle).
 *
 * Features:
 * - Processes one 512-bit message block per operation
 * - Outputs 256-bit hash
 * - Resource-efficient iterative design
 * - Simple ready/start handshake interface
 *
 * Timing:
 * - 1 cycle: IDLE → LOAD
 * - 1 cycle: LOAD → PREPARE
 * - 48 cycles: PREPARE (computing W[16..63])
 * - 64 cycles: PROCESS (64 rounds)
 * - 1 cycle: DONE
 * Total: ~115 cycles per block
 *
 * Interface:
 * - Assert 'start' when ready=1 to begin hashing
 * - Provide 512-bit message block (already padded)
 * - Wait for ready=1, read hash_out
 *
 * Note: This module expects PRE-PADDED input!
 * You must handle padding externally.
 */

module sha256_core (
    input wire clk,
    input wire rst_n,

    // Input interface
    input wire [511:0] message_block,  // 512-bit input block (big-endian)
    input wire start,                   // Start processing

    // Output interface
    output reg [255:0] hash_out,       // 256-bit hash output
    output reg ready                    // Ready for new input
);

    // ========================================================================
    // State Machine States
    // ========================================================================
    localparam [2:0] IDLE    = 3'd0;  // Waiting for input
    localparam [2:0] LOAD    = 3'd1;  // Loading message into W[0..15]
    localparam [2:0] PREPARE = 3'd2;  // Computing W[16..63]
    localparam [2:0] PROCESS = 3'd3;  // Processing 64 rounds
    localparam [2:0] DONE    = 3'd4;  // Finalizing hash

    reg [2:0] state, next_state;
    reg [6:0] round_counter;           // 0-63 for rounds, 16-63 for prepare

    // ========================================================================
    // Hash Values (H) - Persistent across blocks
    // ========================================================================
    reg [31:0] H0, H1, H2, H3, H4, H5, H6, H7;

    // ========================================================================
    // Working Variables (a-h) - Updated each round
    // ========================================================================
    reg [31:0] a, b, c, d, e, f, g, h;

    // ========================================================================
    // Message Schedule (W) - 64 32-bit words
    // ========================================================================
    reg [31:0] W [0:63];
    integer i;  // For loop variable

    // ========================================================================
    // Round Constants (K) - First 32 bits of cube roots of first 64 primes
    // ========================================================================
    function [31:0] K;
        input [5:0] t;
        begin
            case (t)
                6'd0:  K = 32'h428a2f98;
                6'd1:  K = 32'h71374491;
                6'd2:  K = 32'hb5c0fbcf;
                6'd3:  K = 32'he9b5dba5;
                6'd4:  K = 32'h3956c25b;
                6'd5:  K = 32'h59f111f1;
                6'd6:  K = 32'h923f82a4;
                6'd7:  K = 32'hab1c5ed5;
                6'd8:  K = 32'hd807aa98;
                6'd9:  K = 32'h12835b01;
                6'd10: K = 32'h243185be;
                6'd11: K = 32'h550c7dc3;
                6'd12: K = 32'h72be5d74;
                6'd13: K = 32'h80deb1fe;
                6'd14: K = 32'h9bdc06a7;
                6'd15: K = 32'hc19bf174;
                6'd16: K = 32'he49b69c1;
                6'd17: K = 32'hefbe4786;
                6'd18: K = 32'h0fc19dc6;
                6'd19: K = 32'h240ca1cc;
                6'd20: K = 32'h2de92c6f;
                6'd21: K = 32'h4a7484aa;
                6'd22: K = 32'h5cb0a9dc;
                6'd23: K = 32'h76f988da;
                6'd24: K = 32'h983e5152;
                6'd25: K = 32'ha831c66d;
                6'd26: K = 32'hb00327c8;
                6'd27: K = 32'hbf597fc7;
                6'd28: K = 32'hc6e00bf3;
                6'd29: K = 32'hd5a79147;
                6'd30: K = 32'h06ca6351;
                6'd31: K = 32'h14292967;
                6'd32: K = 32'h27b70a85;
                6'd33: K = 32'h2e1b2138;
                6'd34: K = 32'h4d2c6dfc;
                6'd35: K = 32'h53380d13;
                6'd36: K = 32'h650a7354;
                6'd37: K = 32'h766a0abb;
                6'd38: K = 32'h81c2c92e;
                6'd39: K = 32'h92722c85;
                6'd40: K = 32'ha2bfe8a1;
                6'd41: K = 32'ha81a664b;
                6'd42: K = 32'hc24b8b70;
                6'd43: K = 32'hc76c51a3;
                6'd44: K = 32'hd192e819;
                6'd45: K = 32'hd6990624;
                6'd46: K = 32'hf40e3585;
                6'd47: K = 32'h106aa070;
                6'd48: K = 32'h19a4c116;
                6'd49: K = 32'h1e376c08;
                6'd50: K = 32'h2748774c;
                6'd51: K = 32'h34b0bcb5;
                6'd52: K = 32'h391c0cb3;
                6'd53: K = 32'h4ed8aa4a;
                6'd54: K = 32'h5b9cca4f;
                6'd55: K = 32'h682e6ff3;
                6'd56: K = 32'h748f82ee;
                6'd57: K = 32'h78a5636f;
                6'd58: K = 32'h84c87814;
                6'd59: K = 32'h8cc70208;
                6'd60: K = 32'h90befffa;
                6'd61: K = 32'ha4506ceb;
                6'd62: K = 32'hbef9a3f7;
                6'd63: K = 32'hc67178f2;
                default: K = 32'h00000000;
            endcase
        end
    endfunction

    // ========================================================================
    // SHA-256 Functions
    // ========================================================================

    // Rotate right by n bits
    function [31:0] rotr;
        input [31:0] x;
        input [4:0] n;
        begin
            rotr = (x >> n) | (x << (32 - n));
        end
    endfunction

    // Shift right by n bits (logical)
    function [31:0] shr;
        input [31:0] x;
        input [4:0] n;
        begin
            shr = x >> n;
        end
    endfunction

    // Ch(x,y,z) = (x AND y) XOR (NOT x AND z)
    // "Choose": If x then y, else z
    function [31:0] ch;
        input [31:0] x, y, z;
        begin
            ch = (x & y) ^ (~x & z);
        end
    endfunction

    // Maj(x,y,z) = (x AND y) XOR (x AND z) XOR (y AND z)
    // "Majority": Return majority bit value
    function [31:0] maj;
        input [31:0] x, y, z;
        begin
            maj = (x & y) ^ (x & z) ^ (y & z);
        end
    endfunction

    // Σ₀(x) = ROTR²(x) XOR ROTR¹³(x) XOR ROTR²²(x)
    function [31:0] sum0;
        input [31:0] x;
        begin
            sum0 = rotr(x, 5'd2) ^ rotr(x, 5'd13) ^ rotr(x, 5'd22);
        end
    endfunction

    // Σ₁(x) = ROTR⁶(x) XOR ROTR¹¹(x) XOR ROTR²⁵(x)
    function [31:0] sum1;
        input [31:0] x;
        begin
            sum1 = rotr(x, 5'd6) ^ rotr(x, 5'd11) ^ rotr(x, 5'd25);
        end
    endfunction

    // σ₀(x) = ROTR⁷(x) XOR ROTR¹⁸(x) XOR SHR³(x)
    function [31:0] sigma0;
        input [31:0] x;
        begin
            sigma0 = rotr(x, 5'd7) ^ rotr(x, 5'd18) ^ shr(x, 5'd3);
        end
    endfunction

    // σ₁(x) = ROTR¹⁷(x) XOR ROTR¹⁹(x) XOR SHR¹⁰(x)
    function [31:0] sigma1;
        input [31:0] x;
        begin
            sigma1 = rotr(x, 5'd17) ^ rotr(x, 5'd19) ^ shr(x, 5'd10);
        end
    endfunction

    // ========================================================================
    // Temporary Variables for Round Computation
    // ========================================================================
    reg [31:0] T1, T2;

    // ========================================================================
    // Main State Machine
    // ========================================================================
    always @(posedge clk or negedge rst_n) begin
        if (!rst_n) begin
            // Reset to initial state
            state <= IDLE;
            ready <= 1'b1;
            round_counter <= 7'd0;
            hash_out <= 256'd0;

            // Initialize H values (first 32 bits of fractional parts of sqrt of first 8 primes)
            H0 <= 32'h6a09e667;
            H1 <= 32'hbb67ae85;
            H2 <= 32'h3c6ef372;
            H3 <= 32'ha54ff53a;
            H4 <= 32'h510e527f;
            H5 <= 32'h9b05688c;
            H6 <= 32'h1f83d9ab;
            H7 <= 32'h5be0cd19;

            // Initialize W array
            for (i = 0; i < 64; i = i + 1) begin
                W[i] <= 32'd0;
            end

            a <= 32'd0;
            b <= 32'd0;
            c <= 32'd0;
            d <= 32'd0;
            e <= 32'd0;
            f <= 32'd0;
            g <= 32'd0;
            h <= 32'd0;

        end else begin
            case (state)
                // ============================================================
                // IDLE: Wait for start signal
                // ============================================================
                IDLE: begin
                    ready <= 1'b1;
                    if (start) begin
                        state <= LOAD;
                        ready <= 1'b0;
                    end
                end

                // ============================================================
                // LOAD: Load message block into W[0..15]
                // ============================================================
                LOAD: begin
                    // Reset H values for new hash (single-block mode)
                    H0 <= 32'h6a09e667;
                    H1 <= 32'hbb67ae85;
                    H2 <= 32'h3c6ef372;
                    H3 <= 32'ha54ff53a;
                    H4 <= 32'h510e527f;
                    H5 <= 32'h9b05688c;
                    H6 <= 32'h1f83d9ab;
                    H7 <= 32'h5be0cd19;

                    // Split 512-bit message into 16 32-bit words (big-endian)
                    // message_block[511:480] is first word, etc.
                    W[0]  <= message_block[511:480];
                    W[1]  <= message_block[479:448];
                    W[2]  <= message_block[447:416];
                    W[3]  <= message_block[415:384];
                    W[4]  <= message_block[383:352];
                    W[5]  <= message_block[351:320];
                    W[6]  <= message_block[319:288];
                    W[7]  <= message_block[287:256];
                    W[8]  <= message_block[255:224];
                    W[9]  <= message_block[223:192];
                    W[10] <= message_block[191:160];
                    W[11] <= message_block[159:128];
                    W[12] <= message_block[127:96];
                    W[13] <= message_block[95:64];
                    W[14] <= message_block[63:32];
                    W[15] <= message_block[31:0];

                    round_counter <= 7'd16;
                    state <= PREPARE;
                end

                // ============================================================
                // PREPARE: Compute W[16..63] using message schedule
                // ============================================================
                PREPARE: begin
                    // W[t] = σ₁(W[t-2]) + W[t-7] + σ₀(W[t-15]) + W[t-16]
                    W[round_counter] <= sigma1(W[round_counter - 2]) +
                                       W[round_counter - 7] +
                                       sigma0(W[round_counter - 15]) +
                                       W[round_counter - 16];

                    if (round_counter == 7'd63) begin
                        // Message schedule complete, initialize working variables
                        a <= H0;
                        b <= H1;
                        c <= H2;
                        d <= H3;
                        e <= H4;
                        f <= H5;
                        g <= H6;
                        h <= H7;

                        round_counter <= 7'd0;
                        state <= PROCESS;
                    end else begin
                        round_counter <= round_counter + 1;
                    end
                end

                // ============================================================
                // PROCESS: Execute 64 compression rounds
                // ============================================================
                PROCESS: begin
                    // Compute T1 and T2
                    // T₁ = h + Σ₁(e) + Ch(e,f,g) + K[t] + W[t]
                    T1 = h + sum1(e) + ch(e, f, g) + K(round_counter[5:0]) + W[round_counter];

                    // T₂ = Σ₀(a) + Maj(a,b,c)
                    T2 = sum0(a) + maj(a, b, c);

                    // Update working variables
                    h <= g;
                    g <= f;
                    f <= e;
                    e <= d + T1;
                    d <= c;
                    c <= b;
                    b <= a;
                    a <= T1 + T2;

                    if (round_counter == 7'd63) begin
                        state <= DONE;
                    end else begin
                        round_counter <= round_counter + 1;
                    end
                end

                // ============================================================
                // DONE: Add working variables to hash values and output
                // ============================================================
                DONE: begin
                    // Add working variables to hash values
                    H0 <= H0 + a;
                    H1 <= H1 + b;
                    H2 <= H2 + c;
                    H3 <= H3 + d;
                    H4 <= H4 + e;
                    H5 <= H5 + f;
                    H6 <= H6 + g;
                    H7 <= H7 + h;

                    // Concatenate hash values for output
                    hash_out <= {H0 + a, H1 + b, H2 + c, H3 + d,
                                H4 + e, H5 + f, H6 + g, H7 + h};

                    state <= IDLE;
                end

                default: begin
                    state <= IDLE;
                end
            endcase
        end
    end

endmodule

testbench/sha256_tb.v
/*
 * SHA-256 Testbench
 *
 * This testbench verifies the SHA-256 core against NIST test vectors.
 *
 * Test vectors from NIST:
 * https://csrc.nist.gov/projects/cryptographic-standards-and-guidelines/example-values
 *
 * How to run:
 *   iverilog -o sha256_sim ../rtl/sha256_core.v sha256_tb.v
 *   vvp sha256_sim
 *   gtkwave sha256_tb.vcd
 *
 * Expected behavior:
 *   - All test vectors should pass
 *   - No timing violations
 *   - Ready signal properly asserted/deasserted
 */

`timescale 1ns / 1ps

module sha256_tb;

    // ========================================================================
    // Clock and Reset
    // ========================================================================
    reg clk;
    reg rst_n;

    // ========================================================================
    // DUT Interface
    // ========================================================================
    reg [511:0] message_block;
    reg start;
    wire [255:0] hash_out;
    wire ready;

    // ========================================================================
    // Test Control
    // ========================================================================
    integer test_num;
    integer pass_count;
    integer fail_count;
    reg [255:0] expected_hash;

    // ========================================================================
    // Instantiate DUT (Device Under Test)
    // ========================================================================
    sha256_core dut (
        .clk(clk),
        .rst_n(rst_n),
        .message_block(message_block),
        .start(start),
        .hash_out(hash_out),
        .ready(ready)
    );

    // ========================================================================
    // Clock Generation: 100 MHz (10ns period)
    // ========================================================================
    initial begin
        clk = 0;
        forever #5 clk = ~clk;
    end

    // ========================================================================
    // VCD Dump for Waveform Viewing
    // ========================================================================
    initial begin
        $dumpfile("sha256_tb.vcd");
        $dumpvars(0, sha256_tb);
    end

    // ========================================================================
    // Helper Task: Perform one hash operation
    // ========================================================================
    task hash_block;
        input [511:0] msg;
        input [255:0] expected;
        begin
            test_num = test_num + 1;

            // Wait for ready
            while (!ready) @(posedge clk);

            // Apply input
            @(posedge clk);
            message_block = msg;
            start = 1;

            @(posedge clk);
            start = 0;

            // Wait for completion
            while (!ready) @(posedge clk);

            @(posedge clk);

            // Check result
            if (hash_out == expected) begin
                $display("[PASS] Test %0d: Hash matches expected value", test_num);
                pass_count = pass_count + 1;
            end else begin
                $display("[FAIL] Test %0d: Hash mismatch!", test_num);
                $display("  Expected: %064x", expected);
                $display("  Got:      %064x", hash_out);
                fail_count = fail_count + 1;
            end
        end
    endtask

    // ========================================================================
    // Main Test Sequence
    // ========================================================================
    initial begin
        // Initialize
        rst_n = 0;
        start = 0;
        message_block = 512'd0;
        test_num = 0;
        pass_count = 0;
        fail_count = 0;

        $display("========================================");
        $display("SHA-256 Core Testbench");
        $display("========================================");

        // Reset sequence
        #100;
        rst_n = 1;
        #50;

        // ====================================================================
        // Test 1: Empty string ""
        // ====================================================================
        // Padded message: 0x80 followed by zeros, then length (0x00)
        $display("\nTest 1: Empty string");
        hash_block(
            512'h80000000000000000000000000000000000000000000000000000000000000000000000000000000000000000000000000000000000000000000000000000000,
            256'he3b0c44298fc1c149afbf4c8996fb92427ae41e4649b934ca495991b7852b855
        );

        // ====================================================================
        // Test 2: "abc"
        // ====================================================================
        // "abc" = 0x616263
        // Padded: 0x61626380 00...00 00...18 (24 bits = 0x18)
        $display("\nTest 2: 'abc'");
        hash_block(
            512'h61626380000000000000000000000000000000000000000000000000000000000000000000000000000000000000000000000000000000000000000000000018,
            256'hba7816bf8f01cfea414140de5dae2223b00361a396177a9cb410ff61f20015ad
        );

        // ====================================================================
        // Test 3: "hello" (40 bits = 5 bytes)
        // ====================================================================
        // "hello" = 0x68656c6c6f
        // Padded: 0x68656c6c6f80 00...00 00...28 (40 bits = 0x28)
        $display("\nTest 3: 'hello'");
        hash_block(
            512'h68656c6c6f8000000000000000000000000000000000000000000000000000000000000000000000000000000000000000000000000000000000000000000028,
            256'h2cf24dba5fb0a30e26e83b2ac5b9e29e1b161e5c1fa7425e73043362938b9824
        );

        // ====================================================================
        // Test 4: Single block of zeros (testing corner case)
        // ====================================================================
        $display("\nTest 4: Block of zeros with length 0");
        hash_block(
            512'h80000000000000000000000000000000000000000000000000000000000000000000000000000000000000000000000000000000000000000000000000000000,
            256'he3b0c44298fc1c149afbf4c8996fb92427ae41e4649b934ca495991b7852b855
        );

        // ====================================================================
        // Test 5: "test" (32 bits = 4 bytes)
        // ====================================================================
        // "test" = 0x74657374
        // Padded: 0x7465737480 00...00 00...20 (32 bits = 0x20)
        $display("\nTest 5: 'test'");
        hash_block(
            512'h74657374800000000000000000000000000000000000000000000000000000000000000000000000000000000000000000000000000000000000000000000020,
            256'h9f86d081884c7d659a2feaa0c55ad015a3bf4f1b2b0b822cd15d6c15b0f00a08
        );

        // ====================================================================
        // Test 6: Back-to-back operations (test ready/start handshake)
        // ====================================================================
        $display("\nTest 6: Back-to-back 'abc' hashes");
        hash_block(
            512'h61626380000000000000000000000000000000000000000000000000000000000000000000000000000000000000000000000000000000000000000000000018,
            256'hba7816bf8f01cfea414140de5dae2223b00361a396177a9cb410ff61f20015ad
        );
        hash_block(
            512'h61626380000000000000000000000000000000000000000000000000000000000000000000000000000000000000000000000000000000000000000000000018,
            256'hba7816bf8f01cfea414140de5dae2223b00361a396177a9cb410ff61f20015ad
        );

        // ====================================================================
        // Test Summary
        // ====================================================================
        #1000;
        $display("\n========================================");
        $display("Test Summary");
        $display("========================================");
        $display("Total Tests: %0d", test_num);
        $display("Passed:      %0d", pass_count);
        $display("Failed:      %0d", fail_count);

        if (fail_count == 0) begin
            $display("\n*** ALL TESTS PASSED! ***\n");
        end else begin
            $display("\n*** SOME TESTS FAILED! ***\n");
        end

        $display("========================================\n");
        $finish;
    end

    // ========================================================================
    // Timeout Watchdog (prevent infinite simulation)
    // ========================================================================
    initial begin
        #1000000;  // 1ms timeout
        $display("\n[ERROR] Simulation timeout!");
        $finish;
    end

    // ========================================================================
    // Monitor (optional - prints state changes)
    // ========================================================================
    // Uncomment to see detailed state transitions
    /*
    always @(posedge clk) begin
        if (start)
            $display("Time %0t: START asserted", $time);
        if (ready)
            $display("Time %0t: READY asserted", $time);
    end
    */

endmodule

sha256_tb.vcd
$date
	Mon Jan 12 01:03:00 2026
$end
$version
	Icarus Verilog
$end
$timescale
	1ps
$end
$scope module sha256_tb $end
$var wire 1 ! ready $end
$var wire 256 " hash_out [255:0] $end
$var reg 1 # clk $end
$var reg 512 $ message_block [511:0] $end
$var reg 1 % rst_n $end
$var reg 1 & start $end
$var integer 32 ' fail_count [31:0] $end
$var integer 32 ( pass_count [31:0] $end
$var integer 32 ) test_num [31:0] $end
$scope module dut $end
$var wire 1 # clk $end
$var wire 512 * message_block [511:0] $end
$var wire 1 % rst_n $end
$var wire 1 & start $end
$var parameter 3 + DONE $end
$var parameter 3 , IDLE $end
$var parameter 3 - LOAD $end
$var parameter 3 . PREPARE $end
$var parameter 3 / PROCESS $end
$var reg 32 0 H0 [31:0] $end
$var reg 32 1 H1 [31:0] $end
$var reg 32 2 H2 [31:0] $end
$var reg 32 3 H3 [31:0] $end
$var reg 32 4 H4 [31:0] $end
$var reg 32 5 H5 [31:0] $end
$var reg 32 6 H6 [31:0] $end
$var reg 32 7 H7 [31:0] $end
$var reg 32 8 T1 [31:0] $end
$var reg 32 9 T2 [31:0] $end
$var reg 32 : a [31:0] $end
$var reg 32 ; b [31:0] $end
$var reg 32 < c [31:0] $end
$var reg 32 = d [31:0] $end
$var reg 32 > e [31:0] $end
$var reg 32 ? f [31:0] $end
$var reg 32 @ g [31:0] $end
$var reg 32 A h [31:0] $end
$var reg 256 B hash_out [255:0] $end
$var reg 1 ! ready $end
$var reg 7 C round_counter [6:0] $end
$var reg 3 D state [2:0] $end
$var integer 32 E i [31:0] $end
$scope function K $end
$var reg 6 F t [5:0] $end
$upscope $end
$scope function ch $end
$var reg 32 G x [31:0] $end
$var reg 32 H y [31:0] $end
$var reg 32 I z [31:0] $end
$upscope $end
$scope function maj $end
$var reg 32 J x [31:0] $end
$var reg 32 K y [31:0] $end
$var reg 32 L z [31:0] $end
$upscope $end
$scope function rotr $end
$var reg 5 M n [4:0] $end
$var reg 32 N x [31:0] $end
$upscope $end
$scope function shr $end
$var reg 5 O n [4:0] $end
$var reg 32 P x [31:0] $end
$upscope $end
$scope function sigma0 $end
$var reg 32 Q x [31:0] $end
$upscope $end
$scope function sigma1 $end
$var reg 32 R x [31:0] $end
$upscope $end
$scope function sum0 $end
$var reg 32 S x [31:0] $end
$upscope $end
$scope function sum1 $end
$var reg 32 T x [31:0] $end
$upscope $end
$upscope $end
$scope task hash_block $end
$var reg 256 U expected [255:0] $end
$var reg 512 V msg [511:0] $end
$upscope $end
$upscope $end
$enddefinitions $end
$comment Show the parameter values. $end
$dumpall
b11 /
b10 .
b1 -
b0 ,
b100 +
$end
#0
$dumpvars
bx V
bx U
bx T
bx S
bx R
bx Q
bx P
bx O
bx N
bx M
bx L
bx K
bx J
bx I
bx H
bx G
bx F
b1000000 E
b0 D
b0 C
b0 B
b0 A
b0 @
b0 ?
b0 >
b0 =
b0 <
b0 ;
b0 :
bx 9
bx 8
b1011011111000001100110100011001 7
b11111100000111101100110101011 6
b10011011000001010110100010001100 5
b1010001000011100101001001111111 4
b10100101010011111111010100111010 3
b111100011011101111001101110010 2
b10111011011001111010111010000101 1
b1101010000010011110011001100111 0
b0 *
b0 )
b0 (
b0 '
0&
0%
b0 $
0#
b0 "
1!
$end
#5000
b1000000 E
1#
#10000
0#
#15000
b1000000 E
1#
#20000
0#
#25000
b1000000 E
1#
#30000
0#
#35000
b1000000 E
1#
#40000
0#
#45000
b1000000 E
1#
#50000
0#
#55000
b1000000 E
1#
#60000
0#
#65000
b1000000 E
1#
#70000
0#
#75000
b1000000 E
1#
#80000
0#
#85000
b1000000 E
1#
#90000
0#
#95000
b1000000 E
1#
#100000
0#
1%
#105000
1#
#110000
0#
#115000
1#
#120000
0#
#125000
1#
#130000
0#
#135000
1#
#140000
0#
#145000
1#
#150000
0#
b1 )
b1110001110110000110001000100001010011000111111000001110000010100100110101111101111110100110010001001100101101111101110010010010000100111101011100100000111100100011001001001101110010011010011001010010010010101100110010001101101111000010100101011100001010101 U
b10000000000000000000000000000000000000000000000000000000000000000000000000000000000000000000000000000000000000000000000000000000000000000000000000000000000000000000000000000000000000000000000000000000000000000000000000000000000000000000000000000000000000000000000000000000000000000000000000000000000000000000000000000000000000000000000000000000000000000000000000000000000000000000000000000000000000000000000000000000000000000000000000000000000000000000000000000000000000000000000000000000000000000000000000000000 V
#155000
0!
b1 D
1&
b10000000000000000000000000000000000000000000000000000000000000000000000000000000000000000000000000000000000000000000000000000000000000000000000000000000000000000000000000000000000000000000000000000000000000000000000000000000000000000000000000000000000000000000000000000000000000000000000000000000000000000000000000000000000000000000000000000000000000000000000000000000000000000000000000000000000000000000000000000000000000000000000000000000000000000000000000000000000000000000000000000000000000000000000000000000 $
b10000000000000000000000000000000000000000000000000000000000000000000000000000000000000000000000000000000000000000000000000000000000000000000000000000000000000000000000000000000000000000000000000000000000000000000000000000000000000000000000000000000000000000000000000000000000000000000000000000000000000000000000000000000000000000000000000000000000000000000000000000000000000000000000000000000000000000000000000000000000000000000000000000000000000000000000000000000000000000000000000000000000000000000000000000000 *
1#
#160000
0#
#165000
b10 D
b10000 C
0&
1#
#170000
0#
#175000
b10001 C
b0 Q
b0 P
b11 O
b0 N
b10010 M
b0 R
1#
#180000
0#
#185000
b10010 C
b11 O
b10010 M
1#
#190000
0#
#195000
b10011 C
b0 P
b11 O
b0 N
b10010 M
b10000000000000000000000000000000 R
1#
#200000
0#
#205000
b10100 C
b11 O
b10010 M
b0 R
1#
#210000
0#
#215000
b10101 C
b0 P
b11 O
b0 N
b10010 M
b1000000101000000000000 R
1#
#220000
0#
#225000
b10110 C
b11 O
b10010 M
b0 R
1#
#230000
0#
#235000
b10111 C
b0 P
b11 O
b0 N
b10010 M
b100010000000000000100000000000 R
1#
#240000
0#
#245000
b11000 C
b11 O
b10010 M
b0 R
1#
#250000
0#
#255000
b11001 C
b0 P
b11 O
b0 N
b10010 M
b101000010001001010101000010 R
1#
#260000
0#
#265000
b11010 C
b0 P
b11 O
b0 N
b10010 M
b10000000000000000000000000000000 R
1#
#270000
0#
#275000
b11011 C
b0 P
b11 O
b0 N
b10010 M
b1011000000010000000000000000000 R
1#
#280000
0#
#285000
b11100 C
b0 P
b11 O
b0 N
b10010 M
b10000001010000000000000 R
1#
#290000
0#
#295000
b11101 C
b0 P
b11 O
b0 N
b10010 M
b101100010010100000101 R
1#
#300000
0#
#305000
b11110 C
b0 P
b11 O
b0 N
b10010 M
b1100110000000000001100000000000 R
1#
#310000
0#
#315000
b11111 C
b0 P
b11 O
b0 N
b10010 M
b11010110001000100010010110000000 R
1#
#320000
0#
#325000
b100000 C
b10000000000000000000000000000000 Q
b10000000000000000000000000000000 P
b11 O
b10000000000000000000000000000000 N
b10010 M
b10100001000100101010100001000 R
1#
#330000
0#
#335000
b100001 C
b0 Q
b0 P
b11 O
b0 N
b10010 M
b11010110010001011111100101011100 R
1#
#340000
0#
#345000
b100010 C
b1000000101000000000000 Q
b1000000101000000000000 P
b11 O
b1000000101000000000000 N
b10010 M
b11001001001010000010000000000000 R
1#
#350000
0#
#355000
b100011 C
b0 Q
b0 P
b11 O
b0 N
b10010 M
b11000011111100010000000010010100 R
1#
#360000
0#
#365000
b100100 C
b100010000000000000100000000000 Q
b100010000000000000100000000000 P
b11 O
b100010000000000000100000000000 N
b10010 M
b101000010011001010011101100110 R
1#
#370000
0#
#375000
b100101 C
b0 Q
b0 P
b11 O
b0 N
b10010 M
b110100010000110110111000110 R
1#
#380000
0#
#385000
b100110 C
b101000010001001010101000010 Q
b101000010001001010101000010 P
b11 O
b101000010001001010101000010 N
b10010 M
b10100011011110111111000100010110 R
1#
#390000
0#
#395000
b100111 C
b10000000000000000000000000000000 Q
b10000000000000000000000000000000 P
b11 O
b10000000000000000000000000000000 N
b10010 M
b1110001011111001011111010010110 R
1#
#400000
0#
#405000
b101000 C
b1011000000010000000000000000000 Q
b1011000000010000000000000000000 P
b11 O
b1011000000010000000000000000000 N
b10010 M
b11111110110000101101011101001010 R
1#
#410000
0#
#415000
b101001 C
b10000001010000000000000 Q
b10000001010000000000000 P
b11 O
b10000001010000000000000 N
b10010 M
b10100111101101100111111100000000 R
1#
#420000
0#
#425000
b101010 C
b101100010010100000101 Q
b101100010010100000101 P
b11 O
b101100010010100000101 N
b10010 M
b10000001000101011001011010100010 R
1#
#430000
0#
#435000
b101011 C
b1100110000000000001100000000000 Q
b1100110000000000001100000000000 P
b11 O
b1100110000000000001100000000000 N
b10010 M
b10011000101001101110011101101000 R
1#
#440000
0#
#445000
b101100 C
b11010110001000100010010110000000 Q
b11010110001000100010010110000000 P
b11 O
b11010110001000100010010110000000 N
b10010 M
b11101100100000110010000010 R
1#
#450000
0#
#455000
b101101 C
b10100001000100101010100001000 Q
b10100001000100101010100001000 P
b11 O
b10100001000100101010100001000 N
b10010 M
b1011101000111011010011111001001 R
1#
#460000
0#
#465000
b101110 C
b11010110010001011111100101011100 Q
b11010110010001011111100101011100 P
b11 O
b11010110010001011111100101011100 N
b10010 M
b10110001010101101011100100110101 R
1#
#470000
0#
#475000
b101111 C
b11001001001010000010000000000000 Q
b11001001001010000010000000000000 P
b11 O
b11001001001010000010000000000000 N
b10010 M
b11000011110111011100101000010001 R
1#
#480000
0#
#485000
b110000 C
b11000011111100010000000010010100 Q
b11000011111100010000000010010100 P
b11 O
b11000011111100010000000010010100 N
b10010 M
b100100100111000001000001111111 R
1#
#490000
0#
#495000
b110001 C
b101000010011001010011101100110 Q
b101000010011001010011101100110 P
b11 O
b101000010011001010011101100110 N
b10010 M
b11000100100011010010010011101111 R
1#
#500000
0#
#505000
b110010 C
b110100010000110110111000110 Q
b110100010000110110111000110 P
b11 O
b110100010000110110111000110 N
b10010 M
b1011101111001010100110000110000 R
1#
#510000
0#
#515000
b110011 C
b10100011011110111111000100010110 Q
b10100011011110111111000100010110 P
b11 O
b10100011011110111111000100010110 N
b10010 M
b11011110111111101100111001100101 R
1#
#520000
0#
#525000
b110100 C
b1110001011111001011111010010110 Q
b1110001011111001011111010010110 P
b11 O
b1110001011111001011111010010110 N
b10010 M
b101100101000010100100000001101 R
1#
#530000
0#
#535000
b110101 C
b11111110110000101101011101001010 Q
b11111110110000101101011101001010 P
b11 O
b11111110110000101101011101001010 N
b10010 M
b111100000101010011001100101100 R
1#
#540000
0#
#545000
b110110 C
b10100111101101100111111100000000 Q
b10100111101101100111111100000000 P
b11 O
b10100111101101100111111100000000 N
b10010 M
b1110011101100100110101101 R
1#
#550000
0#
#555000
b110111 C
b10000001000101011001011010100010 Q
b10000001000101011001011010100010 P
b11 O
b10000001000101011001011010100010 N
b10010 M
b10110000011001100110011010000 R
1#
#560000
0#
#565000
b111000 C
b10011000101001101110011101101000 Q
b10011000101001101110011101101000 P
b11 O
b10011000101001101110011101101000 N
b10010 M
b1011101011001101101010011000 R
1#
#570000
0#
#575000
b111001 C
b11101100100000110010000010 Q
b11101100100000110010000010 P
b11 O
b11101100100000110010000010 N
b10010 M
b110110000110111000111111100000 R
1#
#580000
0#
#585000
b111010 C
b1011101000111011010011111001001 Q
b1011101000111011010011111001001 P
b11 O
b1011101000111011010011111001001 N
b10010 M
b11010010001100100000101110100110 R
1#
#590000
0#
#595000
b111011 C
b10110001010101101011100100110101 Q
b10110001010101101011100100110101 P
b11 O
b10110001010101101011100100110101 N
b10010 M
b10100110110111000000000111 R
1#
#600000
0#
#605000
b111100 C
b11000011110111011100101000010001 Q
b11000011110111011100101000010001 P
b11 O
b11000011110111011100101000010001 N
b10010 M
b1110101010001100101100001111100 R
1#
#610000
0#
#615000
b111101 C
b100100100111000001000001111111 Q
b100100100111000001000001111111 P
b11 O
b100100100111000001000001111111 N
b10010 M
b111111101010100111100111001 R
1#
#620000
0#
#625000
b111110 C
b11000100100011010010010011101111 Q
b11000100100011010010010011101111 P
b11 O
b11000100100011010010010011101111 N
b10010 M
b11111000000010001101110111000011 R
1#
#630000
0#
#635000
b111111 C
b1011101111001010100110000110000 Q
b1011101111001010100110000110000 P
b11 O
b1011101111001010100110000110000 N
b10010 M
b11011100110010100111011000001000 R
1#
#640000
0#
#645000
b11 D
b0 C
b1011011111000001100110100011001 A
b11111100000111101100110101011 @
b10011011000001010110100010001100 ?
b1010001000011100101001001111111 >
b10100101010011111111010100111010 =
b111100011011101111001101110010 <
b10111011011001111010111010000101 ;
b1101010000010011110011001100111 :
b11011110111111101100111001100101 Q
b11011110111111101100111001100101 P
b11 O
b11011110111111101100111001100101 N
b10010 M
b1011110010000100111000110001000 R
1#
#650000
0#
#655000
b1 C
b1111100000010001000100001001101 :
b1101010000010011110011001100111 ;
b10111011011001111010111010000101 <
b111100011011101111001101110010 =
b11000110001111110001010100010 >
b1010001000011100101001001111111 ?
b10011011000001010110100010001100 @
b11111100000111101100110101011 A
b1000100100001001101011100101 9
b1101010000010011110011001100111 J
b10111011011001111010111010000101 K
b111100011011101111001101110010 L
b1101010000010011110011001100111 S
b1110011011101111110110101101000 8
b0 F
b1010001000011100101001001111111 G
b10011011000001010110100010001100 H
b11111100000111101100110101011 I
b1101010000010011110011001100111 N
b10110 M
b1010001000011100101001001111111 T
1#
#660000
0#
